render_engine_cli/__init__.py
render_engine_cli/cli.py
render_engine_cli/event.py
render_engine_cli/utils.py
render_engine_cli-2025.9.1.dist-info/METADATA
render_engine_cli-2025.9.1.dist-info/WHEEL
render_engine_cli-2025.9.1.dist-info/entry_points.txt
render_engine_cli-2025.9.1.dist-info/top_level.txt
render_engine_cli-2025.9.1.dist-info/RECORD
