Metadata-Version: 2.4
Name: render-engine-cli
Version: 2025.9.1
Summary: Command line tool for the Render Engine static site generator
Project-URL: homepage, https://github.com/render-engine/render-engine-cli/
Project-URL: repository, https://github.com/render-engine/render-engine/
Project-URL: documentation, https://render-engine.readthedocs.io/en/latest/
Requires-Python: >=3.10
Requires-Dist: click>=8.2.1
Requires-Dist: cookiecutter>=2.6.0
Requires-Dist: render-engine>=2025.7.1a1
Requires-Dist: rich>=14.0.0
Requires-Dist: toml>=0.10.2
Requires-Dist: watchfiles>=1.1.0
